rs_csv_reader-0.1.4.dist-info/METADATA
rs_csv_reader-0.1.4.dist-info/WHEEL
csv_reader/__init__.py
csv_reader/csv_reader.abi3.so
rs_csv_reader-0.1.4.dist-info/RECORD
