Metadata-Version: 2.4
Name: rs-csv-reader
Version: 0.1.4
